odoo/addons/l10n_it_fatturapa_out_ddt/README.rst
odoo/addons/l10n_it_fatturapa_out_ddt/__init__.py
odoo/addons/l10n_it_fatturapa_out_ddt/__manifest__.py
odoo/addons/l10n_it_fatturapa_out_ddt/i18n/it.po
odoo/addons/l10n_it_fatturapa_out_ddt/i18n/l10n_it_fatturapa_out_ddt.pot
odoo/addons/l10n_it_fatturapa_out_ddt/models/__init__.py
odoo/addons/l10n_it_fatturapa_out_ddt/models/company.py
odoo/addons/l10n_it_fatturapa_out_ddt/models/fattura_differita_ddt.py
odoo/addons/l10n_it_fatturapa_out_ddt/readme/CONFIGURE.rst
odoo/addons/l10n_it_fatturapa_out_ddt/readme/CONTRIBUTORS.rst
odoo/addons/l10n_it_fatturapa_out_ddt/readme/DESCRIPTION.rst
odoo/addons/l10n_it_fatturapa_out_ddt/readme/USAGE.rst
odoo/addons/l10n_it_fatturapa_out_ddt/static/description/icon.png
odoo/addons/l10n_it_fatturapa_out_ddt/static/description/index.html
odoo/addons/l10n_it_fatturapa_out_ddt/tests/__init__.py
odoo/addons/l10n_it_fatturapa_out_ddt/tests/test_fatturapa_ddt.py
odoo/addons/l10n_it_fatturapa_out_ddt/tests/data/IT06363391001_00006.xml
odoo/addons/l10n_it_fatturapa_out_ddt/tests/data/IT06363391001_00007.xml
odoo/addons/l10n_it_fatturapa_out_ddt/views/res_config_settings_views.xml
odoo/addons/l10n_it_fatturapa_out_ddt/wizard/__init__.py
odoo/addons/l10n_it_fatturapa_out_ddt/wizard/wizard_export_fatturapa.py
odoo/addons/l10n_it_fatturapa_out_ddt/wizard/wizard_export_fatturapa_view.xml
odoo12_addon_l10n_it_fatturapa_out_ddt-12.0.1.4.1.dist-info/METADATA
odoo12_addon_l10n_it_fatturapa_out_ddt-12.0.1.4.1.dist-info/WHEEL
odoo12_addon_l10n_it_fatturapa_out_ddt-12.0.1.4.1.dist-info/top_level.txt
odoo12_addon_l10n_it_fatturapa_out_ddt-12.0.1.4.1.dist-info/RECORD
